{
  "info": {
    "_postman_id": "your-collection-id",
    "name": "HIMTI API",
    "description": "API collection for HIMTI Website",
    "schema": "https://schema.getpostman.com/json/collection/v2.1.0/collection.json"
  },
  "variable": [
    {
      "key": "base_url",
      "value": "http://localhost:4000/api/v1",
      "type": "string"
    },
    {
      "key": "jwt_token",
      "value": "",
      "type": "string"
    }
  ],
  "item": [
    {
      "name": "Auth",
      "item": [
        {
          "name": "Register",
          "request": {
            "method": "POST",
            "header": [
              {
                "key": "Content-Type",
                "value": "application/json"
              }
            ],
            "body": {
              "mode": "raw",
              "raw": "{\n    \"email\": \"user@example.com\",\n    \"password\": \"password123\",\n    \"name\": \"John Doe\"\n}",
              "options": {
                "raw": {
                  "language": "json"
                }
              }
            },
            "url": {
              "raw": "{{base_url}}/auth/register",
              "host": ["{{base_url}}"],
              "path": ["auth", "register"]
            }
          }
        },
        {
          "name": "Login",
          "request": {
            "method": "POST",
            "header": [
              {
                "key": "Content-Type",
                "value": "application/json"
              }
            ],
            "body": {
              "mode": "raw",
              "raw": "{\n    \"email\": \"user@example.com\",\n    \"password\": \"password123\"\n}",
              "options": {
                "raw": {
                  "language": "json"
                }
              }
            },
            "url": {
              "raw": "{{base_url}}/auth/login",
              "host": ["{{base_url}}"],
              "path": ["auth", "login"]
            }
          }
        },
        {
          "name": "Logout",
          "request": {
            "method": "POST",
            "header": [
              {
                "key": "Authorization",
                "value": "Bearer {{jwt_token}}",
                "type": "text"
              }
            ],
            "url": {
              "raw": "{{base_url}}/auth/logout",
              "host": ["{{base_url}}"],
              "path": ["auth", "logout"]
            }
          }
        },
        {
          "name": "Forgot Password",
          "request": {
            "method": "POST",
            "header": [
              {
                "key": "Content-Type",
                "value": "application/json"
              }
            ],
            "body": {
              "mode": "raw",
              "raw": "{\n    \"email\": \"user@example.com\"\n}",
              "options": {
                "raw": {
                  "language": "json"
                }
              }
            },
            "url": {
              "raw": "{{base_url}}/auth/forgot-password",
              "host": ["{{base_url}}"],
              "path": ["auth", "forgot-password"]
            }
          }
        },
        {
          "name": "Reset Password",
          "request": {
            "method": "POST",
            "header": [
              {
                "key": "Content-Type",
                "value": "application/json"
              }
            ],
            "body": {
              "mode": "raw",
              "raw": "{\n    \"email\": \"user@example.com\",\n    \"otp\": \"123456\",\n    \"newPassword\": \"newpassword123\"\n}",
              "options": {
                "raw": {
                  "language": "json"
                }
              }
            },
            "url": {
              "raw": "{{base_url}}/auth/reset-password",
              "host": ["{{base_url}}"],
              "path": ["auth", "reset-password"]
            }
          }
        },
        {
          "name": "Verify OTP",
          "request": {
            "method": "POST",
            "header": [
              {
                "key": "Content-Type",
                "value": "application/json"
              }
            ],
            "body": {
              "mode": "raw",
              "raw": "{\n    \"email\": \"user@example.com\",\n    \"otp\": \"123456\"\n}",
              "options": {
                "raw": {
                  "language": "json"
                }
              }
            },
            "url": {
              "raw": "{{base_url}}/auth/verify-otp",
              "host": ["{{base_url}}"],
              "path": ["auth", "verify-otp"]
            }
          }
        }
      ]
    },
    {
      "name": "User",
      "item": [
        {
          "name": "Profile",
          "item": [
            {
              "name": "Get Profile",
              "request": {
                "method": "GET",
                "header": [
                  {
                    "key": "Authorization",
                    "value": "Bearer {{jwt_token}}",
                    "type": "text"
                  }
                ],
                "url": {
                  "raw": "{{base_url}}/users/me",
                  "host": ["{{base_url}}"],
                  "path": ["users", "me"]
                }
              }
            },
            {
              "name": "Update Profile",
              "request": {
                "method": "PATCH",
                "header": [
                  {
                    "key": "Authorization",
                    "value": "Bearer {{jwt_token}}",
                    "type": "text"
                  }
                ],
                "body": {
                  "mode": "raw",
                  "raw": "{\n    \"name\": \"Updated Name\",\n    \"profile_picture\": \"https://example.com/picture.jpg\"\n}",
                  "options": {
                    "raw": {
                      "language": "json"
                    }
                  }
                },
                "url": {
                  "raw": "{{base_url}}/users/me",
                  "host": ["{{base_url}}"],
                  "path": ["users", "me"]
                }
              }
            }
          ]
        },
        {
          "name": "Forums",
          "item": [
            {
              "name": "Get All Forums",
              "request": {
                "method": "GET",
                "header": [],
                "url": {
                  "raw": "{{base_url}}/forums",
                  "host": ["{{base_url}}"],
                  "path": ["forums"]
                }
              }
            },
            {
              "name": "Get Forum by ID",
              "request": {
                "method": "GET",
                "header": [],
                "url": {
                  "raw": "{{base_url}}/forums/:id",
                  "host": ["{{base_url}}"],
                  "path": ["forums", ":id"],
                  "variable": [
                    {
                      "key": "id",
                      "value": ""
                    }
                  ]
                }
              }
            },
            {
              "name": "Create Forum",
              "request": {
                "method": "POST",
                "header": [
                  {
                    "key": "Authorization",
                    "value": "Bearer {{jwt_token}}",
                    "type": "text"
                  }
                ],
                "body": {
                  "mode": "raw",
                  "raw": "{\n    \"title\": \"New Forum\",\n    \"content\": \"Forum content\",\n    \"thumbnail\": \"https://example.com/thumbnail.jpg\"\n}",
                  "options": {
                    "raw": {
                      "language": "json"
                    }
                  }
                },
                "url": {
                  "raw": "{{base_url}}/forums",
                  "host": ["{{base_url}}"],
                  "path": ["forums"]
                }
              }
            },
            {
              "name": "Like Forum",
              "request": {
                "method": "POST",
                "header": [
                  {
                    "key": "Authorization",
                    "value": "Bearer {{jwt_token}}",
                    "type": "text"
                  }
                ],
                "url": {
                  "raw": "{{base_url}}/forums/:id/like",
                  "host": ["{{base_url}}"],
                  "path": ["forums", ":id", "like"],
                  "variable": [
                    {
                      "key": "id",
                      "value": ""
                    }
                  ]
                }
              }
            },
            {
              "name": "Comment on Forum",
              "request": {
                "method": "POST",
                "header": [
                  {
                    "key": "Authorization",
                    "value": "Bearer {{jwt_token}}",
                    "type": "text"
                  }
                ],
                "body": {
                  "mode": "raw",
                  "raw": "{\n    \"comment\": \"This is a comment\"\n}",
                  "options": {
                    "raw": {
                      "language": "json"
                    }
                  }
                },
                "url": {
                  "raw": "{{base_url}}/forums/:id/comment",
                  "host": ["{{base_url}}"],
                  "path": ["forums", ":id", "comment"],
                  "variable": [
                    {
                      "key": "id",
                      "value": ""
                    }
                  ]
                }
              }
            }
          ]
        },
        {
          "name": "Articles",
          "item": [
            {
              "name": "Get All Articles",
              "request": {
                "method": "GET",
                "header": [],
                "url": {
                  "raw": "{{base_url}}/articles",
                  "host": ["{{base_url}}"],
                  "path": ["articles"]
                }
              }
            },
            {
              "name": "Get Article by ID",
              "request": {
                "method": "GET",
                "header": [],
                "url": {
                  "raw": "{{base_url}}/articles/:id",
                  "host": ["{{base_url}}"],
                  "path": ["articles", ":id"],
                  "variable": [
                    {
                      "key": "id",
                      "value": ""
                    }
                  ]
                }
              }
            },
            {
              "name": "Like Article",
              "request": {
                "method": "POST",
                "header": [
                  {
                    "key": "Authorization",
                    "value": "Bearer {{jwt_token}}",
                    "type": "text"
                  }
                ],
                "url": {
                  "raw": "{{base_url}}/articles/:id/like",
                  "host": ["{{base_url}}"],
                  "path": ["articles", ":id", "like"],
                  "variable": [
                    {
                      "key": "id",
                      "value": ""
                    }
                  ]
                }
              }
            }
          ]
        },
        {
          "name": "Departments",
          "item": [
            {
              "name": "Get All Departments",
              "request": {
                "method": "GET",
                "header": [],
                "url": {
                  "raw": "{{base_url}}/departments",
                  "host": ["{{base_url}}"],
                  "path": ["departments"]
                }
              }
            },
            {
              "name": "Get Department by ID",
              "request": {
                "method": "GET",
                "header": [],
                "url": {
                  "raw": "{{base_url}}/departments/:id",
                  "host": ["{{base_url}}"],
                  "path": ["departments", ":id"],
                  "variable": [
                    {
                      "key": "id",
                      "value": ""
                    }
                  ]
                }
              }
            }
          ]
        },
        {
          "name": "Members",
          "item": [
            {
              "name": "Get All Members",
              "request": {
                "method": "GET",
                "header": [],
                "url": {
                  "raw": "{{base_url}}/members",
                  "host": ["{{base_url}}"],
                  "path": ["members"]
                }
              }
            },
            {
              "name": "Get Member by ID",
              "request": {
                "method": "GET",
                "header": [],
                "url": {
                  "raw": "{{base_url}}/members/:id",
                  "host": ["{{base_url}}"],
                  "path": ["members", ":id"],
                  "variable": [
                    {
                      "key": "id",
                      "value": ""
                    }
                  ]
                }
              }
            }
          ]
        },
        {
          "name": "Events",
          "item": [
            {
              "name": "Get All Events",
              "request": {
                "method": "GET",
                "header": [],
                "url": {
                  "raw": "{{base_url}}/events",
                  "host": ["{{base_url}}"],
                  "path": ["events"]
                }
              }
            },
            {
              "name": "Get Event by ID",
              "request": {
                "method": "GET",
                "header": [],
                "url": {
                  "raw": "{{base_url}}/events/:id",
                  "host": ["{{base_url}}"],
                  "path": ["events", ":id"],
                  "variable": [
                    {
                      "key": "id",
                      "value": ""
                    }
                  ]
                }
              }
            }
          ]
        },
        {
          "name": "Gallery",
          "item": [
            {
              "name": "Get All Gallery Photos",
              "request": {
                "method": "GET",
                "header": [],
                "url": {
                  "raw": "{{base_url}}/gallery",
                  "host": ["{{base_url}}"],
                  "path": ["gallery"]
                }
              }
            },
            {
              "name": "Get Gallery Photos by Event",
              "request": {
                "method": "GET",
                "header": [],
                "url": {
                  "raw": "{{base_url}}/gallery/event/:eventId",
                  "host": ["{{base_url}}"],
                  "path": ["gallery", "event", ":eventId"],
                  "variable": [
                    {
                      "key": "eventId",
                      "value": ""
                    }
                  ]
                }
              }
            }
          ]
        },
        {
          "name": "Bank Data",
          "item": [
            {
              "name": "Get All Bank Data",
              "request": {
                "method": "GET",
                "header": [],
                "url": {
                  "raw": "{{base_url}}/bank-data",
                  "host": ["{{base_url}}"],
                  "path": ["bank-data"]
                }
              }
            },
            {
              "name": "Get Bank Data by ID",
              "request": {
                "method": "GET",
                "header": [],
                "url": {
                  "raw": "{{base_url}}/bank-data/:id",
                  "host": ["{{base_url}}"],
                  "path": ["bank-data", ":id"],
                  "variable": [
                    {
                      "key": "id",
                      "value": ""
                    }
                  ]
                }
              }
            }
          ]
        }
      ]
    },
    {
      "name": "Admin",
      "item": [
        {
          "name": "User Management",
          "item": [
            {
              "name": "Create Super Admin",
              "request": {
                "method": "POST",
                "header": [
                  {
                    "key": "Authorization",
                    "value": "Bearer {{jwt_token}}",
                    "type": "text"
                  }
                ],
                "body": {
                  "mode": "raw",
                  "raw": "{\n    \"email\": \"superadmin@example.com\",\n    \"password\": \"password123\",\n    \"name\": \"Super Admin\"\n}",
                  "options": {
                    "raw": {
                      "language": "json"
                    }
                  }
                },
                "url": {
                  "raw": "{{base_url}}/admin/users/super-admin",
                  "host": ["{{base_url}}"],
                  "path": ["admin", "users", "super-admin"]
                }
              }
            },
            {
              "name": "Create User",
              "request": {
                "method": "POST",
                "header": [
                  {
                    "key": "Authorization",
                    "value": "Bearer {{jwt_token}}",
                    "type": "text"
                  }
                ],
                "body": {
                  "mode": "raw",
                  "raw": "{\n    \"email\": \"user@example.com\",\n    \"password\": \"password123\",\n    \"name\": \"Regular User\",\n    \"role\": \"USER\"\n}",
                  "options": {
                    "raw": {
                      "language": "json"
                    }
                  }
                },
                "url": {
                  "raw": "{{base_url}}/admin/users",
                  "host": ["{{base_url}}"],
                  "path": ["admin", "users"]
                }
              }
            },
            {
              "name": "Get All Users",
              "request": {
                "method": "GET",
                "header": [
                  {
                    "key": "Authorization",
                    "value": "Bearer {{jwt_token}}",
                    "type": "text"
                  }
                ],
                "url": {
                  "raw": "{{base_url}}/admin/users",
                  "host": ["{{base_url}}"],
                  "path": ["admin", "users"]
                }
              }
            },
            {
              "name": "Get User by ID",
              "request": {
                "method": "GET",
                "header": [
                  {
                    "key": "Authorization",
                    "value": "Bearer {{jwt_token}}",
                    "type": "text"
                  }
                ],
                "url": {
                  "raw": "{{base_url}}/admin/users/:id",
                  "host": ["{{base_url}}"],
                  "path": ["admin", "users", ":id"],
                  "variable": [
                    {
                      "key": "id",
                      "value": ""
                    }
                  ]
                }
              }
            },
            {
              "name": "Update User",
              "request": {
                "method": "PATCH",
                "header": [
                  {
                    "key": "Authorization",
                    "value": "Bearer {{jwt_token}}",
                    "type": "text"
                  }
                ],
                "body": {
                  "mode": "raw",
                  "raw": "{\n    \"name\": \"Updated Name\",\n    \"role\": \"ADMIN\"\n}",
                  "options": {
                    "raw": {
                      "language": "json"
                    }
                  }
                },
                "url": {
                  "raw": "{{base_url}}/admin/users/:id",
                  "host": ["{{base_url}}"],
                  "path": ["admin", "users", ":id"],
                  "variable": [
                    {
                      "key": "id",
                      "value": ""
                    }
                  ]
                }
              }
            },
            {
              "name": "Delete User",
              "request": {
                "method": "DELETE",
                "header": [
                  {
                    "key": "Authorization",
                    "value": "Bearer {{jwt_token}}",
                    "type": "text"
                  }
                ],
                "url": {
                  "raw": "{{base_url}}/admin/users/:id",
                  "host": ["{{base_url}}"],
                  "path": ["admin", "users", ":id"],
                  "variable": [
                    {
                      "key": "id",
                      "value": ""
                    }
                  ]
                }
              }
            }
          ]
        },
        {
          "name": "Department Management",
          "item": [
            {
              "name": "Create Department",
              "request": {
                "method": "POST",
                "header": [
                  {
                    "key": "Authorization",
                    "value": "Bearer {{jwt_token}}",
                    "type": "text"
                  }
                ],
                "body": {
                  "mode": "raw",
                  "raw": "{\n    \"name\": \"Department Name\"\n}",
                  "options": {
                    "raw": {
                      "language": "json"
                    }
                  }
                },
                "url": {
                  "raw": "{{base_url}}/admin/departments",
                  "host": ["{{base_url}}"],
                  "path": ["admin", "departments"]
                }
              }
            },
            {
              "name": "Get All Departments",
              "request": {
                "method": "GET",
                "header": [
                  {
                    "key": "Authorization",
                    "value": "Bearer {{jwt_token}}",
                    "type": "text"
                  }
                ],
                "url": {
                  "raw": "{{base_url}}/admin/departments",
                  "host": ["{{base_url}}"],
                  "path": ["admin", "departments"]
                }
              }
            },
            {
              "name": "Get Department by ID",
              "request": {
                "method": "GET",
                "header": [
                  {
                    "key": "Authorization",
                    "value": "Bearer {{jwt_token}}",
                    "type": "text"
                  }
                ],
                "url": {
                  "raw": "{{base_url}}/admin/departments/:id",
                  "host": ["{{base_url}}"],
                  "path": ["admin", "departments", ":id"],
                  "variable": [
                    {
                      "key": "id",
                      "value": ""
                    }
                  ]
                }
              }
            },
            {
              "name": "Update Department",
              "request": {
                "method": "PATCH",
                "header": [
                  {
                    "key": "Authorization",
                    "value": "Bearer {{jwt_token}}",
                    "type": "text"
                  }
                ],
                "body": {
                  "mode": "raw",
                  "raw": "{\n    \"name\": \"Updated Department Name\"\n}",
                  "options": {
                    "raw": {
                      "language": "json"
                    }
                  }
                },
                "url": {
                  "raw": "{{base_url}}/admin/departments/:id",
                  "host": ["{{base_url}}"],
                  "path": ["admin", "departments", ":id"],
                  "variable": [
                    {
                      "key": "id",
                      "value": ""
                    }
                  ]
                }
              }
            },
            {
              "name": "Delete Department",
              "request": {
                "method": "DELETE",
                "header": [
                  {
                    "key": "Authorization",
                    "value": "Bearer {{jwt_token}}",
                    "type": "text"
                  }
                ],
                "url": {
                  "raw": "{{base_url}}/admin/departments/:id",
                  "host": ["{{base_url}}"],
                  "path": ["admin", "departments", ":id"],
                  "variable": [
                    {
                      "key": "id",
                      "value": ""
                    }
                  ]
                }
              }
            }
          ]
        },
        {
          "name": "Division Management",
          "item": [
            {
              "name": "Create Division",
              "request": {
                "method": "POST",
                "header": [
                  {
                    "key": "Authorization",
                    "value": "Bearer {{jwt_token}}",
                    "type": "text"
                  }
                ],
                "body": {
                  "mode": "raw",
                  "raw": "{\n    \"department_id\": \"uuid\",\n    \"division\": \"Division Name\"\n}",
                  "options": {
                    "raw": {
                      "language": "json"
                    }
                  }
                },
                "url": {
                  "raw": "{{base_url}}/admin/divisions",
                  "host": ["{{base_url}}"],
                  "path": ["admin", "divisions"]
                }
              }
            },
            {
              "name": "Get All Divisions",
              "request": {
                "method": "GET",
                "header": [
                  {
                    "key": "Authorization",
                    "value": "Bearer {{jwt_token}}",
                    "type": "text"
                  }
                ],
                "url": {
                  "raw": "{{base_url}}/admin/divisions",
                  "host": ["{{base_url}}"],
                  "path": ["admin", "divisions"]
                }
              }
            },
            {
              "name": "Get Division by ID",
              "request": {
                "method": "GET",
                "header": [
                  {
                    "key": "Authorization",
                    "value": "Bearer {{jwt_token}}",
                    "type": "text"
                  }
                ],
                "url": {
                  "raw": "{{base_url}}/admin/divisions/:id",
                  "host": ["{{base_url}}"],
                  "path": ["admin", "divisions", ":id"],
                  "variable": [
                    {
                      "key": "id",
                      "value": ""
                    }
                  ]
                }
              }
            },
            {
              "name": "Update Division",
              "request": {
                "method": "PATCH",
                "header": [
                  {
                    "key": "Authorization",
                    "value": "Bearer {{jwt_token}}",
                    "type": "text"
                  }
                ],
                "body": {
                  "mode": "raw",
                  "raw": "{\n    \"department_id\": \"uuid\",\n    \"division\": \"Updated Division Name\"\n}",
                  "options": {
                    "raw": {
                      "language": "json"
                    }
                  }
                },
                "url": {
                  "raw": "{{base_url}}/admin/divisions/:id",
                  "host": ["{{base_url}}"],
                  "path": ["admin", "divisions", ":id"],
                  "variable": [
                    {
                      "key": "id",
                      "value": ""
                    }
                  ]
                }
              }
            },
            {
              "name": "Delete Division",
              "request": {
                "method": "DELETE",
                "header": [
                  {
                    "key": "Authorization",
                    "value": "Bearer {{jwt_token}}",
                    "type": "text"
                  }
                ],
                "url": {
                  "raw": "{{base_url}}/admin/divisions/:id",
                  "host": ["{{base_url}}"],
                  "path": ["admin", "divisions", ":id"],
                  "variable": [
                    {
                      "key": "id",
                      "value": ""
                    }
                  ]
                }
              }
            }
          ]
        },
        {
          "name": "Member Management",
          "item": [
            {
              "name": "Create Member",
              "request": {
                "method": "POST",
                "header": [
                  {
                    "key": "Authorization",
                    "value": "Bearer {{jwt_token}}",
                    "type": "text"
                  }
                ],
                "body": {
                  "mode": "raw",
                  "raw": "{\n    \"division_id\": \"uuid\",\n    \"name\": \"Member Name\",\n    \"photo\": \"https://example.com/photo.jpg\",\n    \"position\": \"Member Position\"\n}",
                  "options": {
                    "raw": {
                      "language": "json"
                    }
                  }
                },
                "url": {
                  "raw": "{{base_url}}/admin/members",
                  "host": ["{{base_url}}"],
                  "path": ["admin", "members"]
                }
              }
            },
            {
              "name": "Get All Members",
              "request": {
                "method": "GET",
                "header": [
                  {
                    "key": "Authorization",
                    "value": "Bearer {{jwt_token}}",
                    "type": "text"
                  }
                ],
                "url": {
                  "raw": "{{base_url}}/admin/members",
                  "host": ["{{base_url}}"],
                  "path": ["admin", "members"]
                }
              }
            },
            {
              "name": "Get Member by ID",
              "request": {
                "method": "GET",
                "header": [
                  {
                    "key": "Authorization",
                    "value": "Bearer {{jwt_token}}",
                    "type": "text"
                  }
                ],
                "url": {
                  "raw": "{{base_url}}/admin/members/:id",
                  "host": ["{{base_url}}"],
                  "path": ["admin", "members", ":id"],
                  "variable": [
                    {
                      "key": "id",
                      "value": ""
                    }
                  ]
                }
              }
            },
            {
              "name": "Update Member",
              "request": {
                "method": "PATCH",
                "header": [
                  {
                    "key": "Authorization",
                    "value": "Bearer {{jwt_token}}",
                    "type": "text"
                  }
                ],
                "body": {
                  "mode": "raw",
                  "raw": "{\n    \"division_id\": \"uuid\",\n    \"name\": \"Updated Member Name\",\n    \"photo\": \"https://example.com/new-photo.jpg\",\n    \"position\": \"Updated Position\"\n}",
                  "options": {
                    "raw": {
                      "language": "json"
                    }
                  }
                },
                "url": {
                  "raw": "{{base_url}}/admin/members/:id",
                  "host": ["{{base_url}}"],
                  "path": ["admin", "members", ":id"],
                  "variable": [
                    {
                      "key": "id",
                      "value": ""
                    }
                  ]
                }
              }
            },
            {
              "name": "Delete Member",
              "request": {
                "method": "DELETE",
                "header": [
                  {
                    "key": "Authorization",
                    "value": "Bearer {{jwt_token}}",
                    "type": "text"
                  }
                ],
                "url": {
                  "raw": "{{base_url}}/admin/members/:id",
                  "host": ["{{base_url}}"],
                  "path": ["admin", "members", ":id"],
                  "variable": [
                    {
                      "key": "id",
                      "value": ""
                    }
                  ]
                }
              }
            }
          ]
        },
        {
          "name": "Event Management",
          "item": [
            {
              "name": "Create Event",
              "request": {
                "method": "POST",
                "header": [
                  {
                    "key": "Authorization",
                    "value": "Bearer {{jwt_token}}",
                    "type": "text"
                  }
                ],
                "body": {
                  "mode": "raw",
                  "raw": "{\n    \"name\": \"Event Name\"\n}",
                  "options": {
                    "raw": {
                      "language": "json"
                    }
                  }
                },
                "url": {
                  "raw": "{{base_url}}/admin/events",
                  "host": ["{{base_url}}"],
                  "path": ["admin", "events"]
                }
              }
            },
            {
              "name": "Get All Events",
              "request": {
                "method": "GET",
                "header": [
                  {
                    "key": "Authorization",
                    "value": "Bearer {{jwt_token}}",
                    "type": "text"
                  }
                ],
                "url": {
                  "raw": "{{base_url}}/admin/events",
                  "host": ["{{base_url}}"],
                  "path": ["admin", "events"]
                }
              }
            },
            {
              "name": "Get Event by ID",
              "request": {
                "method": "GET",
                "header": [
                  {
                    "key": "Authorization",
                    "value": "Bearer {{jwt_token}}",
                    "type": "text"
                  }
                ],
                "url": {
                  "raw": "{{base_url}}/admin/events/:id",
                  "host": ["{{base_url}}"],
                  "path": ["admin", "events", ":id"],
                  "variable": [
                    {
                      "key": "id",
                      "value": ""
                    }
                  ]
                }
              }
            },
            {
              "name": "Update Event",
              "request": {
                "method": "PATCH",
                "header": [
                  {
                    "key": "Authorization",
                    "value": "Bearer {{jwt_token}}",
                    "type": "text"
                  }
                ],
                "body": {
                  "mode": "raw",
                  "raw": "{\n    \"name\": \"Updated Event Name\"\n}",
                  "options": {
                    "raw": {
                      "language": "json"
                    }
                  }
                },
                "url": {
                  "raw": "{{base_url}}/admin/events/:id",
                  "host": ["{{base_url}}"],
                  "path": ["admin", "events", ":id"],
                  "variable": [
                    {
                      "key": "id",
                      "value": ""
                    }
                  ]
                }
              }
            },
            {
              "name": "Delete Event",
              "request": {
                "method": "DELETE",
                "header": [
                  {
                    "key": "Authorization",
                    "value": "Bearer {{jwt_token}}",
                    "type": "text"
                  }
                ],
                "url": {
                  "raw": "{{base_url}}/admin/events/:id",
                  "host": ["{{base_url}}"],
                  "path": ["admin", "events", ":id"],
                  "variable": [
                    {
                      "key": "id",
                      "value": ""
                    }
                  ]
                }
              }
            }
          ]
        },
        {
          "name": "Gallery Management",
          "item": [
            {
              "name": "Create Gallery",
              "request": {
                "method": "POST",
                "header": [
                  {
                    "key": "Authorization",
                    "value": "Bearer {{jwt_token}}",
                    "type": "text"
                  }
                ],
                "body": {
                  "mode": "raw",
                  "raw": "{\n    \"event_id\": \"uuid\",\n    \"photo_url\": \"https://example.com/photo.jpg\"\n}",
                  "options": {
                    "raw": {
                      "language": "json"
                    }
                  }
                },
                "url": {
                  "raw": "{{base_url}}/admin/gallery",
                  "host": ["{{base_url}}"],
                  "path": ["admin", "gallery"]
                }
              }
            },
            {
              "name": "Get All Galleries",
              "request": {
                "method": "GET",
                "header": [
                  {
                    "key": "Authorization",
                    "value": "Bearer {{jwt_token}}",
                    "type": "text"
                  }
                ],
                "url": {
                  "raw": "{{base_url}}/admin/gallery",
                  "host": ["{{base_url}}"],
                  "path": ["admin", "gallery"]
                }
              }
            },
            {
              "name": "Get Gallery by ID",
              "request": {
                "method": "GET",
                "header": [
                  {
                    "key": "Authorization",
                    "value": "Bearer {{jwt_token}}",
                    "type": "text"
                  }
                ],
                "url": {
                  "raw": "{{base_url}}/admin/gallery/:id",
                  "host": ["{{base_url}}"],
                  "path": ["admin", "gallery", ":id"],
                  "variable": [
                    {
                      "key": "id",
                      "value": ""
                    }
                  ]
                }
              }
            },
            {
              "name": "Update Gallery",
              "request": {
                "method": "PATCH",
                "header": [
                  {
                    "key": "Authorization",
                    "value": "Bearer {{jwt_token}}",
                    "type": "text"
                  }
                ],
                "body": {
                  "mode": "raw",
                  "raw": "{\n    \"event_id\": \"uuid\",\n    \"photo_url\": \"https://example.com/new-photo.jpg\"\n}",
                  "options": {
                    "raw": {
                      "language": "json"
                    }
                  }
                },
                "url": {
                  "raw": "{{base_url}}/admin/gallery/:id",
                  "host": ["{{base_url}}"],
                  "path": ["admin", "gallery", ":id"],
                  "variable": [
                    {
                      "key": "id",
                      "value": ""
                    }
                  ]
                }
              }
            },
            {
              "name": "Delete Gallery",
              "request": {
                "method": "DELETE",
                "header": [
                  {
                    "key": "Authorization",
                    "value": "Bearer {{jwt_token}}",
                    "type": "text"
                  }
                ],
                "url": {
                  "raw": "{{base_url}}/admin/gallery/:id",
                  "host": ["{{base_url}}"],
                  "path": ["admin", "gallery", ":id"],
                  "variable": [
                    {
                      "key": "id",
                      "value": ""
                    }
                  ]
                }
              }
            }
          ]
        },
        {
          "name": "Bank Data Management",
          "item": [
            {
              "name": "Create Bank Data",
              "request": {
                "method": "POST",
                "header": [
                  {
                    "key": "Authorization",
                    "value": "Bearer {{jwt_token}}",
                    "type": "text"
                  }
                ],
                "body": {
                  "mode": "raw",
                  "raw": "{\n    \"title\": \"Bank Data Title\",\n    \"link\": \"https://example.com/bank-data\"\n}",
                  "options": {
                    "raw": {
                      "language": "json"
                    }
                  }
                },
                "url": {
                  "raw": "{{base_url}}/admin/bank-data",
                  "host": ["{{base_url}}"],
                  "path": ["admin", "bank-data"]
                }
              }
            },
            {
              "name": "Get All Bank Data",
              "request": {
                "method": "GET",
                "header": [
                  {
                    "key": "Authorization",
                    "value": "Bearer {{jwt_token}}",
                    "type": "text"
                  }
                ],
                "url": {
                  "raw": "{{base_url}}/admin/bank-data",
                  "host": ["{{base_url}}"],
                  "path": ["admin", "bank-data"]
                }
              }
            },
            {
              "name": "Get Bank Data by ID",
              "request": {
                "method": "GET",
                "header": [
                  {
                    "key": "Authorization",
                    "value": "Bearer {{jwt_token}}",
                    "type": "text"
                  }
                ],
                "url": {
                  "raw": "{{base_url}}/admin/bank-data/:id",
                  "host": ["{{base_url}}"],
                  "path": ["admin", "bank-data", ":id"],
                  "variable": [
                    {
                      "key": "id",
                      "value": ""
                    }
                  ]
                }
              }
            },
            {
              "name": "Update Bank Data",
              "request": {
                "method": "PATCH",
                "header": [
                  {
                    "key": "Authorization",
                    "value": "Bearer {{jwt_token}}",
                    "type": "text"
                  }
                ],
                "body": {
                  "mode": "raw",
                  "raw": "{\n    \"title\": \"Updated Bank Data Title\",\n    \"link\": \"https://example.com/updated-bank-data\"\n}",
                  "options": {
                    "raw": {
                      "language": "json"
                    }
                  }
                },
                "url": {
                  "raw": "{{base_url}}/admin/bank-data/:id",
                  "host": ["{{base_url}}"],
                  "path": ["admin", "bank-data", ":id"],
                  "variable": [
                    {
                      "key": "id",
                      "value": ""
                    }
                  ]
                }
              }
            },
            {
              "name": "Delete Bank Data",
              "request": {
                "method": "DELETE",
                "header": [
                  {
                    "key": "Authorization",
                    "value": "Bearer {{jwt_token}}",
                    "type": "text"
                  }
                ],
                "url": {
                  "raw": "{{base_url}}/admin/bank-data/:id",
                  "host": ["{{base_url}}"],
                  "path": ["admin", "bank-data", ":id"],
                  "variable": [
                    {
                      "key": "id",
                      "value": ""
                    }
                  ]
                }
              }
            }
          ]
        }
      ]
    }
  ]
} 