{
  "info": {
    "name": "HIMTI API - Part 5",
    "description": "API collection for HIMTI API - Auth endpoints",
    "schema": "https://schema.getpostman.com/json/collection/v2.1.0/collection.json"
  },
  "item": [
    {
      "name": "Auth",
      "item": [
        {
          "name": "Register",
          "request": {
            "method": "POST",
            "header": [
              {
                "key": "Content-Type",
                "value": "application/json",
                "type": "text"
              }
            ],
            "body": {
              "mode": "raw",
              "raw": "{\n    \"email\": \"user@example.com\",\n    \"password\": \"password123\",\n    \"name\": \"John Doe\"\n}"
            },
            "url": {
              "raw": "{{baseUrl}}/auth/register",
              "host": ["{{baseUrl}}"],
              "path": ["auth", "register"]
            },
            "description": "Register a new user"
          },
          "response": []
        },
        {
          "name": "Login",
          "request": {
            "method": "POST",
            "header": [
              {
                "key": "Content-Type",
                "value": "application/json",
                "type": "text"
              }
            ],
            "body": {
              "mode": "raw",
              "raw": "{\n    \"email\": \"user@example.com\",\n    \"password\": \"password123\"\n}"
            },
            "url": {
              "raw": "{{baseUrl}}/auth/login",
              "host": ["{{baseUrl}}"],
              "path": ["auth", "login"]
            },
            "description": "Login with email and password"
          },
          "response": []
        },
        {
          "name": "Logout",
          "request": {
            "method": "POST",
            "header": [
              {
                "key": "Authorization",
                "value": "Bearer {{token}}",
                "type": "text"
              }
            ],
            "url": {
              "raw": "{{baseUrl}}/auth/logout",
              "host": ["{{baseUrl}}"],
              "path": ["auth", "logout"]
            },
            "description": "Logout user (removes HTTP-only cookie)"
          },
          "response": []
        },
        {
          "name": "Forgot Password",
          "request": {
            "method": "POST",
            "header": [
              {
                "key": "Content-Type",
                "value": "application/json",
                "type": "text"
              }
            ],
            "body": {
              "mode": "raw",
              "raw": "{\n    \"email\": \"user@example.com\"\n}"
            },
            "url": {
              "raw": "{{baseUrl}}/auth/forgot-password",
              "host": ["{{baseUrl}}"],
              "path": ["auth", "forgot-password"]
            },
            "description": "Request a password reset OTP"
          },
          "response": []
        },
        {
          "name": "Verify OTP",
          "request": {
            "method": "POST",
            "header": [
              {
                "key": "Content-Type",
                "value": "application/json",
                "type": "text"
              }
            ],
            "body": {
              "mode": "raw",
              "raw": "{\n    \"email\": \"user@example.com\",\n    \"otp\": \"123456\"\n}"
            },
            "url": {
              "raw": "{{baseUrl}}/auth/verify-otp",
              "host": ["{{baseUrl}}"],
              "path": ["auth", "verify-otp"]
            },
            "description": "Verify the OTP sent for password reset"
          },
          "response": []
        },
        {
          "name": "Reset Password",
          "request": {
            "method": "POST",
            "header": [
              {
                "key": "Content-Type",
                "value": "application/json",
                "type": "text"
              }
            ],
            "body": {
              "mode": "raw",
              "raw": "{\n    \"email\": \"user@example.com\",\n    \"otp\": \"123456\",\n    \"newPassword\": \"newpassword123\"\n}"
            },
            "url": {
              "raw": "{{baseUrl}}/auth/reset-password",
              "host": ["{{baseUrl}}"],
              "path": ["auth", "reset-password"]
            },
            "description": "Reset password with valid OTP"
          },
          "response": []
        }
      ]
    }
  ],
  "event": [
    {
      "listen": "prerequest",
      "script": {
        "type": "text/javascript",
        "exec": [""]
      }
    },
    {
      "listen": "test",
      "script": {
        "type": "text/javascript",
        "exec": [""]
      }
    }
  ],
  "variable": [
    {
      "key": "baseUrl",
      "value": "http://localhost:3000",
      "type": "string"
    },
    {
      "key": "token",
      "value": "your-auth-token-here",
      "type": "string"
    }
  ]
} 